chessterm/__init__.py
chessterm/core/__init__.py
chessterm/core/core.py
chessterm/ui/__init__.py
chessterm/ui/common.py
chessterm/ui/cursesui.py
chessterm/ui/main.py
chessterm/ui/textui.py
chess_term-0.1.0.dist-info/METADATA
chess_term-0.1.0.dist-info/WHEEL
chess_term-0.1.0.dist-info/entry_points.txt
chess_term-0.1.0.dist-info/top_level.txt
chess_term-0.1.0.dist-info/zip-safe
chess_term-0.1.0.dist-info/RECORD
