Metadata-Version: 2.1
Name: chess-term
Version: 0.1.0
Summary: Play chess in your terminal
Home-page: https://gitlab.com/OldIronHorse/chess-term
Author: Simon Redding
Author-email: s1m0n.r3dd1ng@gmail.com
License: GPL v3
Keywords: chess,boardgame,terminal
Classifier: License :: OSI Approved :: GNU General Public License v3 (GPLv3)
Classifier: Programming Language :: Python :: 3
Requires-Python: >=3.8
Requires-Dist: click
Requires-Dist: chess
Provides-Extra: dev
Requires-Dist: flake8 ; extra == 'dev'
Requires-Dist: bandit ; extra == 'dev'
Requires-Dist: pytest ; extra == 'dev'
Requires-Dist: pytest-cov ; extra == 'dev'
Requires-Dist: pytest-watch ; extra == 'dev'
Requires-Dist: pytest-mock ; extra == 'dev'
